iMaT/__init__.py
iMaT/__main__.py
iMaT/src/__init__.py
iMaT/src/constants.py
iMaT/src/analysis/__init__.py
iMaT/src/analysis/functions.py
iMaT/src/analysis/main.py
iMaT/src/analysis/utils.py
iMaT/src/cli/__init__.py
iMaT/src/cli/menu_constructors.py
iMaT/src/cli/menu_entries.py
iMaT/src/conversion/__init__.py
iMaT/src/conversion/main.py
iMaT/src/conversion/utils.py
iMaT/src/m21_environment/__init__.py
iMaT/src/m21_environment/main.py
iMaT/src/pattern_search/__init__.py
iMaT/src/pattern_search/functions.py
iMaT/src/pattern_search/main.py
iMaT/src/pattern_search/utils.py
iMaT/src/score_selection/__init__.py
iMaT/src/score_selection/main.py
iMaT/src/score_selection/name_parts.py
iMaT/src/score_selection/select_parts_and_measures.py
iMaT/src/tokenization/__init__.py
iMaT/src/tokenization/main.py
iMaT/src/tokenization/utils.py
iMaT/src/tokenization/refine_results/__init__.py
iMaT/src/tokenization/refine_results/absolute_duration.py
iMaT/src/tokenization/refine_results/calculate_pitch_intervals.py
iMaT/src/tokenization/refine_results/remove_prefixes.py
iMaT/src/tokenization/refine_results/tokens_to_txt.py
iMaT/src/utils/__init__.py
iMaT/src/utils/error_handling.py
iMaT/src/utils/misc.py
iMaT/src/visualizations/__init__.py
iMaT/src/visualizations/analysis_results_graphs.py
iMaT/src/visualizations/m21_integrated.py
iMaT/src/visualizations/main.py
imat-3.2.3.dist-info/LICENSE.txt
imat-3.2.3.dist-info/METADATA
imat-3.2.3.dist-info/WHEEL
imat-3.2.3.dist-info/entry_points.txt
imat-3.2.3.dist-info/top_level.txt
imat-3.2.3.dist-info/RECORD
