Metadata-Version: 2.1
Name: imat
Version: 3.2.3
Summary: Interactive Music Analysis Tool (I-MaT)
Home-page: https://github.com/sebastian-eck/I-MaT
Author: Sebastian Oliver Eck
License: MIT License
Classifier: Programming Language :: Python :: 3
Classifier: Programming Language :: Python :: 3.8
Classifier: Programming Language :: Python :: 3.9
Classifier: Programming Language :: Python :: 3.10
Classifier: License :: OSI Approved :: MIT License
Classifier: Operating System :: Microsoft :: Windows
Classifier: Operating System :: Unix
Classifier: Development Status :: 4 - Beta
Classifier: Environment :: Console
Classifier: Framework :: Matplotlib
Classifier: Intended Audience :: Education
Classifier: Intended Audience :: Science/Research
Classifier: Natural Language :: English
Classifier: Topic :: Documentation :: Sphinx
Classifier: Topic :: Education
Classifier: Topic :: Education :: Computer Aided Instruction (CAI)
Classifier: Topic :: Multimedia :: Sound/Audio :: Analysis
Classifier: Topic :: Multimedia :: Sound/Audio :: MIDI
Classifier: Topic :: Text Processing :: Linguistic
License-File: LICENSE.txt
Requires-Dist: numpy ~=1.23.5
Requires-Dist: matplotlib ~=3.7.1
Requires-Dist: pandas ~=2.0.2
Requires-Dist: music21 ~=8.3.0
Requires-Dist: miditok ~=2.0.6
Requires-Dist: tokenizers ~=0.13.3
Requires-Dist: requests ~=2.31.0
Requires-Dist: openpyxl ~=3.1.2
Requires-Dist: tqdm ~=4.65.0
Requires-Dist: seaborn ~=0.12.2
Requires-Dist: scipy ~=1.10.1
Provides-Extra: doc
Requires-Dist: sphinx <7.0.0 ; extra == 'doc'
Requires-Dist: sphinxcontrib-napoleon ~=0.7 ; extra == 'doc'
Requires-Dist: sphinx-autobuild ; extra == 'doc'
Requires-Dist: myst-parser ; extra == 'doc'
Requires-Dist: sphinx-rtd-theme ~=1.2.0 ; extra == 'doc'
